EquationConnectSDK/EquationConnectAPI.py
EquationConnectSDK/__init__.py
EquationConnectSDK-0.2.0.dist-info/LICENSE
EquationConnectSDK-0.2.0.dist-info/METADATA
EquationConnectSDK-0.2.0.dist-info/WHEEL
EquationConnectSDK-0.2.0.dist-info/top_level.txt
EquationConnectSDK-0.2.0.dist-info/RECORD
