Metadata-Version: 2.1
Name: EquationConnectSDK
Version: 0.2.0
Summary: A Python SDK for interacting with Equation Connect devices.
Home-page: https://github.com/carlesibanez/Equation-Connect-SDK
Author: Carles Ibáñez
Author-email: carles.ibanez.trullen@gmail.com
Classifier: Programming Language :: Python :: 3
Classifier: License :: OSI Approved :: MIT License
Classifier: Operating System :: OS Independent
Requires-Python: >=3.6
License-File: LICENSE
Requires-Dist: requests>=2.32.3
Requires-Dist: Pyrebase4>=4.8.0
